[
    {
        "step_id": "001_custom",
        "data": {
            "input_data": {
                "step_name": "initialization",
                "action": "journey_initialized"
            },
            "output_data": {
                "persona": "council_customer",
                "search_parameters": {
                    "query": "How to get free school meals",
                    "max_results": 5,
                    "language": "en",
                    "country": "uk"
                },
                "search_context": {
                    "search_topic": "How to get free school meals",
                    "persona": "council_customer",
                    "need": "I'm recently been made unemployed and I do not have an income, I'd like to apply for free school meals. I'm keen to know what is the criteria and how quickly I will find out if I'm eligible",
                    "started_at": "2025-08-13T02:20:33+01:00",
                    "search_parameters": {
                        "query": "How to get free school meals",
                        "max_results": 5,
                        "language": "en",
                        "country": "uk"
                    }
                },
                "domain": "manchester.gov.uk",
                "Council Name": "Manchester City Council"
            },
            "metadata": {
                "step_name": "initialization",
                "state_transition": "INITIALIZING -> GOOGLE_SEARCH",
                "search_context_created": true
            }
        }
    },
    {
        "step_id": "002_scout",
        "data": {
            "input_data": {
                "step_name": "google_search",
                "action": "google_search_executed"
            },
            "output_data": {
                "search_parameters": {
                    "query": "How to get free school meals",
                    "max_results": 5,
                    "language": "en",
                    "country": "uk"
                },
                "results": [
                    {
                        "title": "Free School Meals | Manchester City Council",
                        "link": "https://www.manchester.gov.uk/info/500186/education_benefits/7355/free_school_meals",
                        "snippet": "Who is eligible? Your child may qualify for free school meals if you get any of the following: Income Support; income-based Jobseeker's Allowance; income\u00a0..."
                    },
                    {
                        "title": "Free school meals and free school travel | Help for families and ...",
                        "link": "https://www.manchester.gov.uk/info/10050/help_with_the_cost_of_living_crisis/8767/help_for_families_and_children",
                        "snippet": "In Manchester nearly one third of school-age children get free school meals. This would be even higher if all families who could get this support claimed it."
                    },
                    {
                        "title": "Household Support Fund | Manchester City Council",
                        "link": "https://www.manchester.gov.uk/info/200008/benefits_and_support/8251/household_support_fund",
                        "snippet": "Support for families with children eligible for Free School Meals. The scheme ... get \u00a3130. Only one payment will be made per household. Payments. If you\u00a0..."
                    },
                    {
                        "title": "School holidays | Help for families and children | Manchester City ...",
                        "link": "https://www.manchester.gov.uk/info/10050/help_with_the_cost_of_living_crisis/8767/help_for_families_and_children/2",
                        "snippet": "Families with children who are eligible for free school meals during term time will receive the following payments for each eligible child, during the school\u00a0..."
                    },
                    {
                        "title": "Who can get one | Apply for a primary school travel pass ...",
                        "link": "https://www.manchester.gov.uk/info/100005/schools_education_and_childcare/7049/apply_for_a_primary_school_travel_pass",
                        "snippet": "Children aged 4 to 11 who get free school meals, or whose parents get maximum Working Tax Credits or Universal Credit if they live more than 2 miles from school\u00a0..."
                    },
                    {
                        "title": "Who can get one | Apply for a secondary school travel pass ...",
                        "link": "https://www.manchester.gov.uk/info/100005/schools_education_and_childcare/7051/apply_for_a_secondary_school_travel_pass",
                        "snippet": "Children aged 11 to 16 \u00b7 Gets free school meals due to low income and claim Universal Credits \u00b7 Attends one of their three nearest suitable secondary schools\u00a0..."
                    },
                    {
                        "title": "Education benefits | Manchester City Council",
                        "link": "https://www.manchester.gov.uk/info/500186/education_benefits",
                        "snippet": "Education benefits. Free School Meals. Was this page helpful? Was this page helpful? Fields marked * cannot be left blank. Yes; No. What were you doing? *"
                    },
                    {
                        "title": "Free and cheap ways to get online | Help for families and children ...",
                        "link": "https://www.manchester.gov.uk/info/10050/help_with_the_cost_of_living_crisis/8767/help_for_families_and_children/7",
                        "snippet": "Free school meals and free school travel \u00b7 School holidays \u00b7 Help with school uniform costs \u00b7 Childcare offer \u00b7 Health advice and food vouchers \u00b7 Money in a\u00a0..."
                    },
                    {
                        "title": "Help with school uniform costs | Help for families and children ...",
                        "link": "https://www.manchester.gov.uk/info/10050/help_with_the_cost_of_living_crisis/8767/help_for_families_and_children/3",
                        "snippet": "... benefits or your children receives free school meals. Please check with your housing association for any support they may provide and how to apply. Martin\u00a0..."
                    },
                    {
                        "title": "Who can get one | Apply for a secondary school cycle voucher ...",
                        "link": "https://www.manchester.gov.uk/info/100005/schools_education_and_childcare/7050/apply_for_a_secondary_school_cycle_voucher",
                        "snippet": "Children aged 11 to 16 \u00b7 Gets free school meals due to low income and claim Universal Credits \u00b7 Attends one of their three nearest suitable secondary schools\u00a0..."
                    }
                ],
                "persona_applied": "council_customer"
            },
            "metadata": {
                "step_name": "google_search",
                "search_successful": true,
                "next_state": "list_analysis"
            }
        }
    },
    {
        "step_id": "003_analyst",
        "data": {
            "input_data": {
                "step_name": "list_analysis",
                "action": "list_analysis_completed"
            },
            "output_data": {
                "analysis_result": {
                    "summary": "Analysis completed"
                },
                "pilot_decision": {
                    "action": "continue",
                    "confidence": 0.8,
                    "selected_links": {
                        "id": "rec_1",
                        "url": "https://www.manchester.gov.uk/info/500186/education_benefits/7355/free_school_meals",
                        "title": "Free School Meals | Manchester City Council",
                        "confidence": 90,
                        "strengths": [
                            "Directly pertinent to the search criteria for council customer information needs on free school meals",
                            "Provides eligibility guidelines"
                        ],
                        "reasoning": "This link provides a direct resource for learning about Free School Meals, a key topic for council customer information on this subject. The page also offers detailed eligibility guidelines.",
                        "rank": 1
                    }
                },
                "analysis_output": {
                    "raw_result": {
                        "Summary": {
                            "status": "RECOMMENDATIONS FOUND",
                            "totalItems": "10",
                            "recommendations": "5"
                        },
                        "Recommendations": [
                            {
                                "Number": "1",
                                "Title": "Free School Meals | Manchester City Council",
                                "Source": "https://www.manchester.gov.uk/info/500186/education_benefits/7355/free_school_meals",
                                "Key Strengths": [
                                    "Directly pertinent to the search criteria for council customer information needs on free school meals",
                                    "Provides eligibility guidelines"
                                ],
                                "Confidence": "90",
                                "Reasoning": "This link provides a direct resource for learning about Free School Meals, a key topic for council customer information on this subject. The page also offers detailed eligibility guidelines."
                            },
                            {
                                "Number": "3",
                                "Title": "Household Support Fund | Manchester City Council",
                                "Source": "https://www.manchester.gov.uk/info/200008/benefits_and_support/8251/household_support_fund",
                                "Key Strengths": [
                                    "Mentions Free School Meals as a criterion for eligibility",
                                    "Offers further financial support to households with children eligible for Free School Meals"
                                ],
                                "Confidence": "85",
                                "Reasoning": "The Household Support Fund provides additional financial assistance to families who have children eligible for Free School Meals, making it a relevant resource for council customers."
                            },
                            {
                                "Number": "4",
                                "Title": "School holidays | Help for families and children | Manchester City ...",
                                "Source": "https://www.manchester.gov.uk/info/10050/help_with_the_cost_of_living_crisis/8767/help_for_families_and_children/2",
                                "Key Strengths": [
                                    "Details financial support for families with children eligible for free school meals during school holidays",
                                    "Provides specific amounts for each eligible child"
                                ],
                                "Confidence": "80",
                                "Reasoning": "This link offers financial aid to families with children eligible for Free School Meals during school holidays, making it a valuable resource for council customers."
                            },
                            {
                                "Number": "5",
                                "Title": "Who can get one | Apply for a primary school travel pass ...",
                                "Source": "https://www.manchester.gov.uk/info/100005/schools_education_and_childcare/7049/apply_for_a_primary_school_travel_pass",
                                "Key Strengths": [
                                    "Eligibility for free school travel pass is tied to free school meals eligibility",
                                    "Helpful for families with young children who qualify for Free School Meals"
                                ],
                                "Confidence": "75",
                                "Reasoning": "The eligibility criteria for a primary school travel pass includes receiving Free School Meals, making it a relevant resource for council customers."
                            },
                            {
                                "Number": "6",
                                "Title": "Who can get one | Apply for a secondary school travel pass ...",
                                "Source": "https://www.manchester.gov.uk/info/100005/schools_education_and_childcare/7051/apply_for_a_secondary_school_travel_pass",
                                "Key Strengths": [
                                    "Eligibility for a secondary school travel pass is tied to free school meals eligibility",
                                    "Helpful for families with older children who qualify for Free School Meals"
                                ],
                                "Confidence": "70",
                                "Reasoning": "The eligibility criteria for a secondary school travel pass includes receiving Free School Meals, making it a relevant resource for council customers."
                            }
                        ],
                        "Analysis Notes": "While many of the search results provide useful information related to free school meals and associated benefits, direct resources like application forms or detailed eligibility guidelines were more prioritized in the recommendations.",
                        "Recommendations Notes": "The top five recommendations cover a range of age groups for children and different types of financial support, addressing the needs of a variety of council customers."
                    },
                    "has_recommendations": "RECOMMENDATIONS FOUND",
                    "confidence_scores": [
                        "90",
                        "85",
                        "80",
                        "75",
                        "70"
                    ],
                    "options": {
                        "max_recommendations": 5,
                        "min_confidence": 60,
                        "include_reasoning": true,
                        "output_format": "structured"
                    },
                    "average_confidence": 80,
                    "max_confidence": "90"
                },
                "pilot_output": {
                    "recommendations": [
                        {
                            "Number": "1",
                            "Title": "Free School Meals | Manchester City Council",
                            "Source": "https://www.manchester.gov.uk/info/500186/education_benefits/7355/free_school_meals",
                            "Reasoning": "This link provides a direct resource for learning about Free School Meals, a key topic for council customer information on this subject. The page also offers detailed eligibility guidelines.",
                            "Confidence": "90"
                        },
                        {
                            "Number": "4",
                            "Title": "School holidays | Help for families and children | Manchester City ...",
                            "Source": "https://www.manchester.gov.uk/info/10050/help_with_the_cost_of_living_crisis/8767/help_for_families_and_children/2",
                            "Reasoning": "This link offers financial aid specifically during school holidays to families with children eligible for Free School Meals.",
                            "Confidence": "80"
                        },
                        {
                            "Number": "3",
                            "Title": "Household Support Fund | Manchester City Council",
                            "Source": "https://www.manchester.gov.uk/info/200008/benefits_and_support/8251/household_support_fund",
                            "Reasoning": "The Household Support Fund provides additional financial assistance to families who have children eligible for Free School Meals.",
                            "Confidence": "85"
                        }
                    ]
                }
            },
            "metadata": {
                "step_name": "list_analysis",
                "analyst_used": "ListAnalyst",
                "pilot_used": "ListPilot",
                "next_state": "link_processing"
            }
        }
    },
    {
        "step_id": "004_custom",
        "data": {
            "input_data": {
                "step_name": "link_processing",
                "action": "links_processed"
            },
            "output_data": {
                "processed_links": [
                    "https://www.manchester.gov.uk/info/500186/education_benefits/7355/free_school_meals"
                ],
                "failed_links": [],
                "process_output": [
                    {
                        "url": "https://www.manchester.gov.uk/info/500186/education_benefits/7355/free_school_meals",
                        "analysis": {
                            "url": "https://www.manchester.gov.uk/info/500186/education_benefits/7355/free_school_meals",
                            "context": {
                                "user_need": "access information",
                                "accessibility_priority": "medium",
                                "user_personas": [],
                                "fallback_required": true,
                                "context": {
                                    "search_topic": "How to get free school meals",
                                    "persona": "council_customer",
                                    "need": "I'm recently been made unemployed and I do not have an income, I'd like to apply for free school meals. I'm keen to know what is the criteria and how quickly I will find out if I'm eligible",
                                    "started_at": "2025-08-13T02:20:33+01:00",
                                    "search_parameters": {
                                        "query": "How to get free school meals",
                                        "max_results": 5,
                                        "language": "en",
                                        "country": "uk"
                                    }
                                },
                                "persona": {
                                    "persona_type": "council_customer",
                                    "expertise_level": "intermediate",
                                    "patience_level": "medium",
                                    "search_intent": "find_council_services_information",
                                    "time_constraints": "moderate",
                                    "quality_expectations": "high",
                                    "accessibility_priority": "high",
                                    "content_preferences": [
                                        "official_sources",
                                        "accessible_formats",
                                        "current_information"
                                    ],
                                    "personas": [
                                        "general_public",
                                        "accessibility_aware"
                                    ]
                                }
                            },
                            "timestamp": "2025-08-13T02:21:02+01:00",
                            "fetch_attempted": true,
                            "fetch_successful": true,
                            "http_status": 200,
                            "content_type": "text/html; charset=UTF-8",
                            "content_length": 18731,
                            "response_time": 0.2,
                            "redirects": [],
                            "technical_assessment": {
                                "score": 90,
                                "max_score": 100,
                                "issues": [],
                                "strengths": [
                                    "Successful HTTP response (200)",
                                    "Fast response time (0.2s)",
                                    "Content successfully retrieved (18731 bytes)",
                                    "Direct access (no redirects)"
                                ],
                                "status_interpretation": {
                                    "status": "success",
                                    "action": "proceed",
                                    "confidence": 95
                                }
                            },
                            "accessibility_assessment": {
                                "score": 90,
                                "max_score": 100,
                                "issues": [],
                                "recommendations": [],
                                "content_type_assessment": {
                                    "accessibility_score": 90,
                                    "user_friendly": true,
                                    "requires_plugin": false,
                                    "mobile_compatible": true,
                                    "recommendation": "proceed"
                                },
                                "user_persona_impacts": []
                            },
                            "recommendation": {
                                "action": "proceed",
                                "confidence": 95,
                                "reason": "Link appears suitable for user needs",
                                "overall_score": 74,
                                "component_scores": {
                                    "technical": 90,
                                    "accessibility": 90,
                                    "match": 50
                                },
                                "next_steps": [
                                    "Follow the link to access the content"
                                ],
                                "alternatives_needed": false
                            }
                        },
                        "processing_time": 0.20331883430480957,
                        "status": "success"
                    }
                ]
            },
            "metadata": {
                "step_name": "link_processing",
                "batch_size": 2,
                "analyst_used": "LinkAnalyst",
                "has_remaining_links": false
            }
        }
    },
    {
        "step_id": "005_scout",
        "data": {
            "input_data": {
                "step_name": "content_retrieval",
                "action": "content_retrieved"
            },
            "output_data": {
                "retrieved_urls": [
                    "https://www.manchester.gov.uk/info/500186/education_benefits/7355/free_school_meals"
                ],
                "content_types": {
                    "html": 1
                },
                "retrieved_content": [
                    {
                        "url": "https://www.manchester.gov.uk/info/500186/education_benefits/7355/free_school_meals",
                        "content": " The extracted clean, semantically structured HTML containing the central editorial content of the page is as follows:\n\n```\n<main id=\"main-content\">\n   <div class=\"container document\" id=\"content\">\n      <section>\n         <h1 class=\"with-icon\" id=\"column_nav\">\n            <a class=\"mcc-icon-benefits-and-support mcc-icon-200008\" href=\"https://www.manchester.gov.uk/info/200008/benefits_and_support\">\n               <span>Benefits and support</span>\n            </a>Free School Meals</h1>\n         <article>\n            <h3>Manchester schools</h3>\n            <p>We can only provide free school meals if your child's school is in <a href=\"https://www.manchester.gov.uk/manchesterarea\">the area covered by Manchester City Council</a>. If it isn't, you'll need to <a href=\"https://www.gov.uk/apply-free-school-meals\">find out which authority is responsible</a> for the school&nbsp;and contact them for advice.</p>\n            <h3>Who is eligible?</h3>\n            <ul>\n               <li>&nbsp;Income Support</li>\n               <li>&nbsp;income-based Jobseeker's Allowance</li>\n               <li>&nbsp;income-related Employment and Support Allowance</li>\n               <li>&nbsp;the guaranteed part of Pension Credit</li>\n               <li>&nbsp;Child Tax Credit (as long as your annual gross income is &pound;16,190 or less and you don\u2019t get Working Tax Credit)</li>\n               <li>&nbsp;Working Tax Credit run-off after you come off Working Tax Credit</li>\n               <li>&nbsp;Universal Credit that you applied for on, or after, 1 April 2018. As long as your household income is less than &pound;7,400 a year after tax, not including any benefits</li>\n            </ul>\n            <h3>Additional information</h3>\n            <ul>\n               <li><span id=\"cke_bm_113S\" style=\"display:none\">&nbsp;</span>In addition, ALL children in Reception, Year 1 and Year 2 can get free school meals - whatever your income. However, if you have one of the qualifying incomes it will help the school if you tell them this, so they can get extra funding.</li>\n               <li>Children who are younger than the mandatory age for starting school can also get free school meals.</li>\n               <li>Your child may also qualify if you are an asylum seeker, or if they receive any of these benefits directly, instead of through a parent or guardian.</li>\n            </ul>\n            <p class=\"well\">If your child qualifies and attends a Trafford school, but you do not live in Trafford, you will be sent a supermarket voucher automatically through your school.<span id=\"cke_bm_113E\" style=\"display:none\">&nbsp;</span></p>\n            <p>Please note: If your school doesn't appear on the list provided in the form or you have a specific query, you'll need to contact the school directly.</p>\n         </article>\n      </section>\n   </div>\n</main>\n```",
                        "content_type": "html",
                        "scout_used": "HTMLScout",
                        "retrieval_time": 18.06461787223816,
                        "status": "success"
                    }
                ]
            },
            "metadata": {
                "step_name": "content_retrieval",
                "scouts_used": [
                    "HTMLScout"
                ],
                "next_state": "content_analysis"
            }
        }
    },
    {
        "step_id": "006_analyst",
        "data": {
            "input_data": {
                "step_name": "content_analysis",
                "action": "content_analyzed"
            },
            "output_data": {
                "analyzed_content": [
                    {
                        "url": "https://www.manchester.gov.uk/info/500186/education_benefits/7355/free_school_meals",
                        "analysis": {
                            "persona": "Council Resident",
                            "Reason": [
                                {
                                    "need": "I'm recently been made unemployed and I'd like to apply for free school meals. I'm keen to know what is the criteria and how quickly I will find out if I'm eligible",
                                    "answer_quality": "The content answers this question well, providing a clear list of qualifying incomes that allow residents to receive free school meals.",
                                    "confidence": "85%",
                                    "reasoning": "The content lists the specific qualifying incomes and even provides additional information about children under mandatory school age can also qualify. Unfortunately, the content does not specify how quickly a resident will find out if they are eligible for free school meals.",
                                    "next_actions": "Contact the Child Benefits Service or the school directly to apply for free school meals."
                                }
                            ],
                            "overall_assessment": "The content is informative and addresses the core concerns of council residents who may be seeking information on eligibility criteria for free school meals. However, there is a key gap in the content as it does not specify how quickly a resident will find out if they are eligible once an application has been made."
                        },
                        "content_type": "html",
                        "analysis_time": 5.8695008754730225,
                        "status": "success"
                    }
                ],
                "analyzed_urls": [
                    "https://www.manchester.gov.uk/info/500186/education_benefits/7355/free_school_meals"
                ],
                "content_types_analyzed": {
                    "html": 1
                }
            },
            "metadata": {
                "step_name": "content_analysis",
                "analyst_used": "ContentAnalyst",
                "persona_applied": "council_customer",
                "next_state": "journey_decision"
            }
        }
    },
    {
        "step_id": "007_pilot",
        "data": {
            "input_data": {
                "step_name": "journey_decision",
                "action": "journey_decision_completed"
            },
            "output_data": {
                "journey_analysis_summary": {
                    "summary": "Analysis completed"
                },
                "journey_analysis": {
                    "journey_id": "20250813_022033-manchester.gov.uk",
                    "analysis_timestamp": "2025-08-13T02:21:26+01:00",
                    "analysis_duration": 0.001,
                    "recommendation": "stopped_success",
                    "confidence": 95,
                    "reasoning": "Sufficient high-quality content found - goal achieved",
                    "metrics": {
                        "basic": {
                            "total_steps": 6,
                            "duration_minutes": 0.8833333333333333,
                            "tokens_consumed": 6691,
                            "tokens_remaining": 23309,
                            "token_utilization_percentage": 22.3,
                            "average_tokens_per_step": 1115.17
                        },
                        "token_analysis": {
                            "status": "comfortable",
                            "remaining_percentage": 77.7,
                            "urgency_score": 0,
                            "estimated_remaining_steps": 20,
                            "consumption_rate": 1115.17,
                            "should_conserve": false,
                            "emergency_stop_recommended": false
                        },
                        "progression_analysis": {
                            "total_steps": 6,
                            "step_types_distribution": {
                                "custom": 2,
                                "scout": 2,
                                "analyst": 2
                            },
                            "recent_steps_count": 5,
                            "recent_step_types": [
                                "scout",
                                "analyst",
                                "custom",
                                "scout",
                                "analyst"
                            ],
                            "successful_steps": 0,
                            "failed_steps": 0,
                            "success_rate": 0,
                            "repetitive_pattern_score": 2,
                            "shows_progress": false,
                            "stagnation_detected": false
                        },
                        "content_quality": {
                            "content_steps_count": 1,
                            "average_quality_score": 1,
                            "max_quality_score": "85",
                            "quality_scores": [
                                "85"
                            ],
                            "quality_trend": "stable",
                            "unique_sources_count": 1,
                            "has_good_content": true,
                            "consistent_good_content": "85",
                            "content_diversity": 1
                        },
                        "persona_analysis": {
                            "persona_type": "council_customer",
                            "expertise_level": "intermediate",
                            "patience_level": "medium",
                            "duration_fatigue_percentage": 12.62,
                            "steps_fatigue_percentage": 50,
                            "overall_fatigue_score": 50,
                            "expected_quality_threshold": 60,
                            "patience_exceeded": false,
                            "boredom_likely": false
                        },
                        "engagement_analysis": {
                            "duration_minutes": 0.8833333333333333,
                            "total_steps": 6,
                            "boredom_indicators": {
                                "excessive_duration": false,
                                "too_many_steps": false,
                                "no_recent_progress": true,
                                "repetitive_failures": false
                            },
                            "boredom_score": 25,
                            "user_likely_bored": false,
                            "engagement_declining": false
                        },
                        "efficiency_analysis": {
                            "efficiency_score": 65,
                            "efficiency_factors": [
                                "Fast completion time"
                            ],
                            "is_efficient": true,
                            "needs_optimization": false
                        }
                    },
                    "analysis_results": {
                        "stop_factors": [
                            "Sufficient high-quality content found - goal achieved"
                        ],
                        "continue_factors": [],
                        "risk_factors": [
                            "Limited progress - may need strategy change"
                        ],
                        "optimization_suggestions": []
                    },
                    "alternative_actions": [
                        "continue_google"
                    ],
                    "risk_factors": [
                        "Diminishing returns",
                        "Token waste"
                    ],
                    "next_step_suggestions": [
                        "Review and compile found content",
                        "Consider content synthesis"
                    ],
                    "journey_summary": {
                        "journey_id": "20250813_022033-manchester.gov.uk",
                        "start_time": "2025-08-13T02:20:33+01:00",
                        "current_time": "2025-08-13T02:21:26+01:00",
                        "duration_seconds": 53,
                        "status": "active",
                        "token_allocation": 30000,
                        "tokens_consumed": 6691,
                        "tokens_remaining": 23309,
                        "token_utilization_percentage": 22.3,
                        "token_status": "available",
                        "total_steps": 6,
                        "call_statistics": {
                            "scout": 2,
                            "analyst": 2,
                            "pilot": 0,
                            "custom": 2,
                            "total": 6
                        },
                        "token_statistics": {
                            "scout": {
                                "calls": 2,
                                "tokens": 2883,
                                "avg_per_call": 1441.5
                            },
                            "analyst": {
                                "calls": 2,
                                "tokens": 3808,
                                "avg_per_call": 1904
                            },
                            "pilot": {
                                "calls": 0,
                                "tokens": 0,
                                "avg_per_call": 0
                            },
                            "custom": {
                                "calls": 2,
                                "tokens": 0,
                                "avg_per_call": 0
                            }
                        },
                        "average_tokens_per_step": 1115.17
                    }
                },
                "final_decision": {
                    "recommendation": "stopped_success",
                    "confidence": 95,
                    "reasoning": "Sufficient high-quality content found - goal achieved"
                },
                "journey_statistics": {
                    "journey_id": "20250813_022033-manchester.gov.uk",
                    "start_time": "2025-08-13T02:20:33+01:00",
                    "current_time": "2025-08-13T02:21:26+01:00",
                    "duration_seconds": 53,
                    "status": "active",
                    "token_allocation": 30000,
                    "tokens_consumed": 6691,
                    "tokens_remaining": 23309,
                    "token_utilization_percentage": 22.3,
                    "token_status": "available",
                    "total_steps": 6,
                    "call_statistics": {
                        "scout": 2,
                        "analyst": 2,
                        "pilot": 0,
                        "custom": 2,
                        "total": 6
                    },
                    "token_statistics": {
                        "scout": {
                            "calls": 2,
                            "tokens": 2883,
                            "avg_per_call": 1441.5
                        },
                        "analyst": {
                            "calls": 2,
                            "tokens": 3808,
                            "avg_per_call": 1904
                        },
                        "pilot": {
                            "calls": 0,
                            "tokens": 0,
                            "avg_per_call": 0
                        },
                        "custom": {
                            "calls": 2,
                            "tokens": 0,
                            "avg_per_call": 0
                        }
                    },
                    "average_tokens_per_step": 1115.17
                }
            },
            "metadata": {
                "step_name": "journey_decision",
                "analyst_used": "JourneyAnalyst",
                "pilot_used": "JourneyPilot",
                "journey_completed": true,
                "next_state": "stopped_success"
            }
        }
    }
]