{
    "journey_type": "coach_council_customer",
    "process_outcome": "stopped_success",
    "tokens_used": 2902,
    "steps_taken": 7,
    "total_duration": 36.927,
    "execution_start": "2025-08-08T15:31:49+01:00",
    "execution_end": "2025-08-08T15:32:26+01:00",
    "journey_metrics": {
        "journey_type": "coach_council_customer",
        "execution_start": 1754663509.850233,
        "states_executed": [
            {
                "state": "initializing",
                "iteration": 1,
                "success": true,
                "duration": 0.002
            },
            {
                "state": "google_search",
                "iteration": 2,
                "success": true,
                "duration": 0.319
            },
            {
                "state": "list_analysis",
                "iteration": 3,
                "success": true,
                "duration": 25.505
            },
            {
                "state": "link_processing",
                "iteration": 4,
                "success": true,
                "duration": 0.23
            },
            {
                "state": "content_retrieval",
                "iteration": 5,
                "success": true,
                "duration": 5.56
            },
            {
                "state": "content_analysis",
                "iteration": 6,
                "success": true,
                "duration": 5.297
            },
            {
                "state": "journey_decision",
                "iteration": 7,
                "success": true,
                "duration": 0.009
            }
        ],
        "iterations_completed": 7,
        "total_tokens_used": 0,
        "errors_encountered": []
    },
    "journey_results": {
        "google_search": {
            "query": "Report missed bin",
            "results": [
                {
                    "title": "Report a missed bin or box collection",
                    "link": "https://www.brighton-hove.gov.uk/rubbish-recycling-and-streets/bins-and-collections/report-missed-bin-or-box-collection",
                    "snippet": "If your rubbish, recycling or garden waste bin hasn't been collected, please wait until after 3pm on your collection day to let us know."
                },
                {
                    "title": "Report a missed bin or box collection",
                    "link": "https://www.brighton-hove.gov.uk/report-missed-bin-or-box-collection",
                    "snippet": "Report a missed bin or box collection. Use this form to report a missed collection of: Environmental Services"
                },
                {
                    "title": "Rubbish, recycling and streets",
                    "link": "https://www.brighton-hove.gov.uk/rubbish-recycling-and-streets",
                    "snippet": "Check your collection dates, report a missed collection, get a new bin or box, and find out more about bins and collections in the city. Recycling. Find out\u00a0..."
                },
                {
                    "title": "Get a new bin or box, or report an unused one",
                    "link": "https://www.brighton-hove.gov.uk/rubbish-recycling-and-streets/rubbish/get-new-bin-or-box-or-report-unused-one",
                    "snippet": "We recommend that you put your property number on your bins to avoid them going missing. Ask us for a different size. You can ask us for a bigger bin or box."
                },
                {
                    "title": "Bins and collections",
                    "link": "https://www.brighton-hove.gov.uk/rubbish-recycling-and-streets/bins-and-collections",
                    "snippet": "Check your collection dates, report a missed collection, get a new bin or box, and find out more about bins and collections in the city."
                },
                {
                    "title": "Latest service updates | Brighton & Hove City Council",
                    "link": "https://www.brighton-hove.gov.uk/rubbish-recycling-and-streets/update",
                    "snippet": "... problem on the streets and what to do with your business waste. Check collection days and download calendars Report a missed bin or box collection Report\u00a0..."
                },
                {
                    "title": "Contact us about household bins",
                    "link": "https://www.brighton-hove.gov.uk/rubbish-recycling-and-streets/contact-us-about-household-bins",
                    "snippet": "Contact us about household bins. Find out how to contact us about household bins. Before you contact us, do you need to: report a missed bin collection\u00a0..."
                },
                {
                    "title": "Report a problem and request a clean-up",
                    "link": "https://www.brighton-hove.gov.uk/rubbish-recycling-and-streets/streets/report-problem-and-request-clean",
                    "snippet": "litter and dog mess; waste problems caused by a business; dead animals - not missing pets; weeds. You'll need to tell us where the problem is and\u00a0..."
                },
                {
                    "title": "Report a problem",
                    "link": "https://www.brighton-hove.gov.uk/topic/report-problem",
                    "snippet": "Report a missed bin or box collection. If your rubbish, recycling or garden waste bin hasn't been collected, please wait until after 3pm on your collection day\u00a0..."
                },
                {
                    "title": "Garden waste collections - terms and conditions",
                    "link": "https://www.brighton-hove.gov.uk/rubbish-recycling-and-streets/rubbish/garden-waste-collections-terms-and-conditions",
                    "snippet": "39. The Customer can report a missed collection online or by telephoning 01273 292 929. 40. The Council will aim to return within 2 days to collect\u00a0..."
                }
            ],
            "count": 10,
            "executed_at": "2025-08-08T15:31:50+01:00"
        },
        "list_analysis": {
            "analysis_result": "{\n    \"raw_result\": {\n        \"Summary\": {\n            \"status\": \"RECOMMENDATIONS FOUND\",\n            \"totalItems\": \"10\",\n            \"recommendations\": \"5\"\n        },\n        \"Recommendations\": [\n            {\n                \"Number\": \"1\",\n                \"Title\": \"Report a missed bin or box collection\",\n                \"Source\": \"https:\\/\\/www.brighton-hove.gov.uk\\/report-missed-bin-or-box-collection\",\n                \"Key Strengths\": [\n                    \"Direct link to report a missed bin or box collection\",\n                    \"Provides form to report the issue\"\n                ],\n                \"Confidence\": \"90\",\n                \"Reasoning\": \"This link directly provides a form for users to report a missed bin or box collection, making it the most relevant to the customer information needs.\"\n            },\n            {\n                \"Number\": \"3\",\n                \"Title\": \"Rubbish, recycling and streets\",\n                \"Source\": \"https:\\/\\/www.brighton-hove.gov.uk\\/rubbish-recycling-and-streets\",\n                \"Key Strengths\": [\n                    \"Offers information about bins, collections, and rubbish & recycling in general\",\n                    \"Includes a link to check collection days\"\n                ],\n                \"Confidence\": \"80\",\n                \"Reasoning\": \"While not directly reporting a missed bin or box collection, this resource offers additional useful information related to the customer's needs.\"\n            },\n            {\n                \"Number\": \"7\",\n                \"Title\": \"Contact us about household bins\",\n                \"Source\": \"https:\\/\\/www.brighton-hove.gov.uk\\/rubbish-recycling-and-streets\\/contact-us-about-household-bins\",\n                \"Key Strengths\": [\n                    \"Provides contact information for reporting a missed bin or box collection\"\n                ],\n                \"Confidence\": \"80\",\n                \"Reasoning\": \"This resource offers a way for users to contact the city council directly regarding household bins, which includes their ability to report a missed bin or box collection.\"\n            },\n            {\n                \"Number\": \"9\",\n                \"Title\": \"Report a problem\",\n                \"Source\": \"https:\\/\\/www.brighton-hove.gov.uk\\/topic\\/report-problem\",\n                \"Key Strengths\": [\n                    \"Allows users to report various problems, including missed bin or box collection\"\n                ],\n                \"Confidence\": \"70\",\n                \"Reasoning\": \"Although not a dedicated link for reporting a missed bin or box collection, this resource provides an avenue for customers to report the issue indirectly.\"\n            },\n            {\n                \"Number\": \"9\",\n                \"Title\": \"Report a missed bin or box collection\",\n                \"Source\": \"https:\\/\\/www.brighton-hove.gov.uk\\/rubbish-recycling-and-streets\\/bins-and-collections\",\n                \"Key Strengths\": [\n                    \"Contains information about missed bin collections and allows users to report the issue\"\n                ],\n                \"Confidence\": \"70\",\n                \"Reasoning\": \"This resource addresses both general information about bins and collections as well as an opportunity for users to report a missed bin or box collection.\"\n            }\n        ],\n        \"Analysis Notes\": \"The search results focused on the city council's rubbish, recycling, and streets services. Although most of the results were pertinent to the subject matter, they varied in relevance to the specific customer request for council customer information needs related to reporting a missed bin or box collection.\",\n        \"Recommendations Notes\": \"The recommendations provided above are organized by level of confidence in their ability to directly address the user's need for information on how to report a missed bin or box collection. It is essential to note that while there are several resources available, not all provide a simple process or direct access to reporting the issue.\"\n    },\n    \"has_recommendations\": \"RECOMMENDATIONS FOUND\",\n    \"confidence_scores\": [\n        \"90\",\n        \"80\",\n        \"80\",\n        \"70\",\n        \"70\"\n    ],\n    \"options\": {\n        \"max_recommendations\": 5,\n        \"min_confidence\": 60,\n        \"include_reasoning\": true,\n        \"output_format\": \"structured\"\n    },\n    \"average_confidence\": 78,\n    \"max_confidence\": \"90\"\n}",
            "pilot_result": " {\n  \"result\": [\n    {\n      \"Number\": \"1\",\n      \"Title\": \"Report a missed bin or box collection\",\n      \"Source\": \"https:\\/\\/www.brighton-hove.gov.uk\\/report-missed-bin-or-box-collection\",\n      \"Reasoning\": \"This link directly provides a form for users to report a missed bin or box collection, making it the most relevant to the customer information needs with a high confidence score.\",\n      \"Confidence\": \"90\"\n    },\n    {\n      \"Number\": \"7\",\n      \"Title\": \"Contact us about household bins\",\n      \"Source\": \"https:\\/\\/www.brighton-hove.gov.uk\\/rubbish-recycling-and-streets\\/contact-us-about-household-bins\",\n      \"Reasoning\": \"This resource offers a way for users to contact the city council directly regarding household bins, which includes their ability to report a missed bin or box collection.\",\n      \"Confidence\": \"80\"\n    },\n    {\n      \"Number\": \"3\",\n      \"Title\": \"Rubbish, recycling and streets\",\n      \"Source\": \"https:\\/\\/www.brighton-hove.gov.uk\\/rubbish-recycling-and-streets\",\n      \"Reasoning\": \"While not directly reporting a missed bin or box collection, this resource offers additional useful information related to the customer's needs.\",\n      \"Confidence\": \"80\"\n    }\n  ],\n  \"max_selections\": 3,\n  \"min_confidence\": 0.6\n}",
            "decision": {
                "action": "continue",
                "confidence": 0.8,
                "selected_links": {
                    "id": "rec_1",
                    "url": "https://www.brighton-hove.gov.uk/report-missed-bin-or-box-collection",
                    "title": "Report a missed bin or box collection",
                    "confidence": 90,
                    "strengths": [
                        "Direct link to report a missed bin or box collection",
                        "Provides form to report the issue"
                    ],
                    "reasoning": "This link directly provides a form for users to report a missed bin or box collection, making it the most relevant to the customer information needs.",
                    "rank": 1
                }
            },
            "executed_at": "2025-08-08T15:32:15+01:00"
        },
        "link_processing": [
            {
                "processed_links": [
                    {
                        "url": "https://www.brighton-hove.gov.uk/report-missed-bin-or-box-collection",
                        "analysis": {
                            "url": "https://www.brighton-hove.gov.uk/report-missed-bin-or-box-collection",
                            "context": {
                                "user_need": "access information",
                                "accessibility_priority": "medium",
                                "user_personas": [],
                                "fallback_required": true,
                                "context": {
                                    "search_topic": "Report missed bin",
                                    "persona": "council_customer",
                                    "need": "I forgot to put my bin out and need to report that I would like it collected.",
                                    "started_at": "2025-08-08T15:31:49+01:00",
                                    "search_parameters": {
                                        "query": "Report missed bin",
                                        "max_results": 5,
                                        "language": "en",
                                        "country": "uk"
                                    }
                                },
                                "persona": {
                                    "persona_type": "council_customer",
                                    "expertise_level": "intermediate",
                                    "patience_level": "medium",
                                    "search_intent": "find_council_services_information",
                                    "time_constraints": "moderate",
                                    "quality_expectations": "high",
                                    "accessibility_priority": "high",
                                    "content_preferences": [
                                        "official_sources",
                                        "accessible_formats",
                                        "current_information"
                                    ],
                                    "personas": [
                                        "general_public",
                                        "accessibility_aware"
                                    ]
                                }
                            },
                            "timestamp": "2025-08-08T15:32:15+01:00",
                            "fetch_attempted": true,
                            "fetch_successful": true,
                            "http_status": 200,
                            "content_type": "text/html; charset=UTF-8",
                            "content_length": 175165,
                            "response_time": 0.227,
                            "redirects": [],
                            "technical_assessment": {
                                "score": 90,
                                "max_score": 100,
                                "issues": [],
                                "strengths": [
                                    "Successful HTTP response (200)",
                                    "Fast response time (0.227s)",
                                    "Content successfully retrieved (175165 bytes)",
                                    "Direct access (no redirects)"
                                ],
                                "status_interpretation": {
                                    "status": "success",
                                    "action": "proceed",
                                    "confidence": 95
                                }
                            },
                            "accessibility_assessment": {
                                "score": 90,
                                "max_score": 100,
                                "issues": [],
                                "recommendations": [],
                                "content_type_assessment": {
                                    "accessibility_score": 90,
                                    "user_friendly": true,
                                    "requires_plugin": false,
                                    "mobile_compatible": true,
                                    "recommendation": "proceed"
                                },
                                "user_persona_impacts": []
                            },
                            "recommendation": {
                                "action": "proceed",
                                "confidence": 95,
                                "reason": "Link appears suitable for user needs",
                                "overall_score": 74,
                                "component_scores": {
                                    "technical": 90,
                                    "accessibility": 90,
                                    "match": 50
                                },
                                "next_steps": [
                                    "Follow the link to access the content"
                                ],
                                "alternatives_needed": false
                            }
                        },
                        "processing_time": 0.22780895233154297,
                        "status": "success"
                    }
                ],
                "failed_links": [],
                "executed_at": "2025-08-08T15:32:15+01:00"
            }
        ],
        "content_analysis": {
            "analyzed_content": [
                {
                    "url": "https://www.brighton-hove.gov.uk/report-missed-bin-or-box-collection",
                    "analysis": {
                        "persona": "Council Resident",
                        "Reason": [
                            {
                                "need": "I forgot to put my bin out and need to report that I would like it collected.",
                                "answer_quality": "The content partially addresses this need",
                                "confidence": "70%",
                                "reasoning": "Although the content does provide a means for reporting a missed bin or box collection, there is no explicit mention of what to do when a bin was not put out, which might lead some residents like myself to think it doesn't apply in this case. I would have preferred if the website explained specifically what actions I should take when I forget to put my bin out.",
                                "next_actions": "I will report the missed collection by going through the provided reporting process as best as I can understand, and mentioning that I forgot to put the bin out in the description."
                            }
                        ],
                        "overall_assessment": "While the content provides a means for reporting missed collections, it does not offer a detailed explanation of how to handle minor oversights like forgetting to put a bin out. This creates some confusion among residents. To improve, the website could provide more detailed instructions and clarify common situations that might require reporting."
                    },
                    "content_type": "html",
                    "analysis_time": 5.291429042816162,
                    "status": "success"
                }
            ],
            "failed_analyses": [],
            "executed_at": "2025-08-08T15:32:26+01:00"
        },
        "journey_decision": {
            "journey_analysis": {
                "journey_id": "20250808_153149-brighton-hove.gov.uk",
                "analysis_timestamp": "2025-08-08T15:32:26+01:00",
                "analysis_duration": 0,
                "recommendation": "stopped_success",
                "confidence": 95,
                "reasoning": "Sufficient high-quality content found - goal achieved",
                "metrics": {
                    "basic": {
                        "total_steps": 5,
                        "duration_minutes": 0.6166666666666667,
                        "tokens_consumed": 2902,
                        "tokens_remaining": 27098,
                        "token_utilization_percentage": 9.67,
                        "average_tokens_per_step": 580.4
                    },
                    "token_analysis": {
                        "status": "comfortable",
                        "remaining_percentage": 90.33,
                        "urgency_score": 0,
                        "estimated_remaining_steps": 46,
                        "consumption_rate": 580.4,
                        "should_conserve": false,
                        "emergency_stop_recommended": false
                    },
                    "progression_analysis": {
                        "total_steps": 5,
                        "step_types_distribution": {
                            "custom": 2,
                            "scout": 1,
                            "analyst": 2
                        },
                        "recent_steps_count": 5,
                        "recent_step_types": [
                            "custom",
                            "scout",
                            "analyst",
                            "custom",
                            "analyst"
                        ],
                        "successful_steps": 0,
                        "failed_steps": 0,
                        "success_rate": 0,
                        "repetitive_pattern_score": 2,
                        "shows_progress": false,
                        "stagnation_detected": false
                    },
                    "content_quality": {
                        "content_steps_count": 1,
                        "average_quality_score": 1,
                        "max_quality_score": "70",
                        "quality_scores": [
                            "70"
                        ],
                        "quality_trend": "stable",
                        "unique_sources_count": 1,
                        "has_good_content": true,
                        "consistent_good_content": "70",
                        "content_diversity": 1
                    },
                    "persona_analysis": {
                        "persona_type": "council_customer",
                        "expertise_level": "intermediate",
                        "patience_level": "medium",
                        "duration_fatigue_percentage": 8.81,
                        "steps_fatigue_percentage": 41.67,
                        "overall_fatigue_score": 41.67,
                        "expected_quality_threshold": 60,
                        "patience_exceeded": false,
                        "boredom_likely": false
                    },
                    "engagement_analysis": {
                        "duration_minutes": 0.6166666666666667,
                        "total_steps": 5,
                        "boredom_indicators": {
                            "excessive_duration": false,
                            "too_many_steps": false,
                            "no_recent_progress": true,
                            "repetitive_failures": false
                        },
                        "boredom_score": 25,
                        "user_likely_bored": false,
                        "engagement_declining": false
                    },
                    "efficiency_analysis": {
                        "efficiency_score": 100,
                        "efficiency_factors": [
                            "Low token consumption per step",
                            "Efficient step count",
                            "Fast completion time"
                        ],
                        "is_efficient": true,
                        "needs_optimization": false
                    }
                },
                "analysis_results": {
                    "stop_factors": [
                        "Sufficient high-quality content found - goal achieved"
                    ],
                    "continue_factors": [],
                    "risk_factors": [
                        "Limited progress - may need strategy change"
                    ],
                    "optimization_suggestions": []
                },
                "alternative_actions": [
                    "continue_google"
                ],
                "risk_factors": [
                    "Diminishing returns",
                    "Token waste"
                ],
                "next_step_suggestions": [
                    "Review and compile found content",
                    "Consider content synthesis"
                ],
                "journey_summary": {
                    "journey_id": "20250808_153149-brighton-hove.gov.uk",
                    "start_time": "2025-08-08T15:31:49+01:00",
                    "current_time": "2025-08-08T15:32:26+01:00",
                    "duration_seconds": 37,
                    "status": "active",
                    "token_allocation": 30000,
                    "tokens_consumed": 2902,
                    "tokens_remaining": 27098,
                    "token_utilization_percentage": 9.67,
                    "token_status": "available",
                    "total_steps": 5,
                    "call_statistics": {
                        "scout": 1,
                        "analyst": 2,
                        "pilot": 0,
                        "custom": 2,
                        "total": 5
                    },
                    "token_statistics": {
                        "scout": {
                            "calls": 1,
                            "tokens": 0,
                            "avg_per_call": 0
                        },
                        "analyst": {
                            "calls": 2,
                            "tokens": 2902,
                            "avg_per_call": 1451
                        },
                        "pilot": {
                            "calls": 0,
                            "tokens": 0,
                            "avg_per_call": 0
                        },
                        "custom": {
                            "calls": 2,
                            "tokens": 0,
                            "avg_per_call": 0
                        }
                    },
                    "average_tokens_per_step": 580.4
                }
            },
            "final_decision": {
                "plan_id": "plan_68960a7abcffb",
                "generated_at": "2025-08-08T15:32:26+01:00",
                "journey_id": "20250808_153149-brighton-hove.gov.uk",
                "based_on_analysis": {
                    "recommendation": "stopped_success",
                    "confidence": 95,
                    "reasoning": "Sufficient high-quality content found - goal achieved"
                },
                "primary_action": {
                    "action_type": "complete_journey",
                    "service": "journey_scout",
                    "description": "Complete the journey and compile results",
                    "execution_steps": [
                        "1. Compile all journey results and findings",
                        "2. Generate comprehensive summary",
                        "3. Evaluate overall journey success",
                        "4. Mark journey as completed",
                        "5. Provide final recommendations for user"
                    ],
                    "parameters": {
                        "completion_reason": "Sufficient high-quality content found - goal achieved",
                        "include_summary": true,
                        "include_recommendations": true,
                        "result_format": "comprehensive"
                    },
                    "estimated_token_cost": 800,
                    "estimated_duration": 1,
                    "requirements_check": {
                        "all_requirements_met": true,
                        "individual_checks": {
                            "completion_reason": true
                        }
                    }
                },
                "fallback_plans": [],
                "resource_requirements": {
                    "estimated_tokens": 800,
                    "estimated_duration": 1,
                    "memory_requirements": "low",
                    "external_service_calls": 1
                },
                "success_criteria": {
                    "primary_success_metric": "Action completed without errors",
                    "quality_thresholds": {
                        "minimum_quality_score": 60
                    },
                    "performance_criteria": {
                        "max_duration": 1.5
                    }
                },
                "risk_mitigation": {
                    "token_exhaustion": "Monitor token usage and stop if threshold exceeded",
                    "service_failure": "Implement retry logic with exponential backoff",
                    "poor_results": "Have fallback strategies ready"
                },
                "monitoring_points": {
                    "pre_execution": "Verify all requirements are met",
                    "mid_execution": "Check progress and resource consumption",
                    "post_execution": "Evaluate results and success metrics"
                },
                "options": {
                    "include_fallback_plans": true,
                    "include_resource_estimates": true,
                    "include_success_metrics": true
                }
            },
            "parsed_decision": {
                "recommendation": "stopped_success",
                "confidence": 95,
                "reasoning": "Sufficient high-quality content found - goal achieved"
            },
            "executed_at": "2025-08-08T15:32:26+01:00"
        }
    },
    "journey_outcome": true,
    "next_state": "stopped_success",
    "reason": "Sufficient high-quality content found - goal achieved",
    "execution_duration": 0.009,
    "journey_scout_summary": {
        "journey_id": "20250808_153149-brighton-hove.gov.uk",
        "start_time": "2025-08-08T15:31:49+01:00",
        "current_time": "2025-08-08T15:32:26+01:00",
        "duration_seconds": 37,
        "status": "active",
        "token_allocation": 30000,
        "tokens_consumed": 2902,
        "tokens_remaining": 27098,
        "token_utilization_percentage": 9.67,
        "token_status": "available",
        "total_steps": 6,
        "call_statistics": {
            "scout": 1,
            "analyst": 2,
            "pilot": 1,
            "custom": 2,
            "total": 6
        },
        "token_statistics": {
            "scout": {
                "calls": 1,
                "tokens": 0,
                "avg_per_call": 0
            },
            "analyst": {
                "calls": 2,
                "tokens": 2902,
                "avg_per_call": 1451
            },
            "pilot": {
                "calls": 1,
                "tokens": 0,
                "avg_per_call": 0
            },
            "custom": {
                "calls": 2,
                "tokens": 0,
                "avg_per_call": 0
            }
        },
        "average_tokens_per_step": 483.67
    }
}