{
    "journey_type": "coach_council_customer",
    "process_outcome": "try_chat",
    "tokens_used": 5582,
    "steps_taken": 10,
    "total_duration": 38.994,
    "execution_start": "2025-08-11T00:56:32+01:00",
    "execution_end": "2025-08-11T00:57:11+01:00",
    "journey_metrics": {
        "journey_type": "coach_council_customer",
        "execution_start": 1754870192.722012,
        "states_executed": [
            {
                "state": "initializing",
                "iteration": 1,
                "success": true,
                "duration": 0.001
            },
            {
                "state": "google_search",
                "iteration": 2,
                "success": true,
                "duration": 0.436
            },
            {
                "state": "list_analysis",
                "iteration": 3,
                "success": true,
                "duration": 26.393
            },
            {
                "state": "link_processing",
                "iteration": 4,
                "success": true,
                "duration": 0.641
            },
            {
                "state": "content_retrieval",
                "iteration": 5,
                "success": true,
                "duration": 6.245
            },
            {
                "state": "content_analysis",
                "iteration": 6,
                "success": true,
                "duration": 5.261
            },
            {
                "state": "journey_decision",
                "iteration": 7,
                "success": true,
                "duration": 0.009
            }
        ],
        "iterations_completed": 7,
        "total_tokens_used": 0,
        "errors_encountered": [
            {
                "iteration": 8,
                "state": "try_chat",
                "error": "Unknown journey state: try_chat",
                "error_type": "Exception",
                "timestamp": "2025-08-11T00:57:11+01:00"
            },
            {
                "iteration": 9,
                "state": "try_chat",
                "error": "Unknown journey state: try_chat",
                "error_type": "Exception",
                "timestamp": "2025-08-11T00:57:11+01:00"
            },
            {
                "iteration": 10,
                "state": "try_chat",
                "error": "Unknown journey state: try_chat",
                "error_type": "Exception",
                "timestamp": "2025-08-11T00:57:11+01:00"
            }
        ]
    },
    "journey_results": {
        "google_search": {
            "query": "planning permission solar panels",
            "results": [
                {
                    "title": "Do I need permission? - Mid Suffolk District Council - babergh.gov ...",
                    "link": "https://www.midsuffolk.gov.uk/do-i-need-permission-",
                    "snippet": "Find information and guidance about planning permission, if you wish to make a change to your home."
                },
                {
                    "title": "Energy efficiency in historic buildings - Mid Suffolk District Council ...",
                    "link": "https://midsuffolk.gov.uk/energy-efficiency-in-historic-buildings",
                    "snippet": "There are also similar exemptions for the private renting of buildings where Minimum Energy Efficiency Standards (MEES) apply. Do I need planning permission? ,."
                },
                {
                    "title": "Planning - Babergh District Council - babergh.gov.uk / midsuffolk ...",
                    "link": "https://midsuffolk.gov.uk/en/web/babergh/planning",
                    "snippet": "Planning applications, pre-application advice, decision appeals and planning enforcement. ... Apply for planning permission from us, learn our fees and charges\u00a0..."
                },
                {
                    "title": "Funding agreed for \u00a35.2million pavilion as part of district's sporting ...",
                    "link": "https://www.midsuffolk.gov.uk/w/funding-agreed-for-5.2million-pavilion-as-part-of-district-s-sporting-upgrade%C2%A0",
                    "snippet": "Jul 8, 2025 ... The pavilion, which already has planning permission, will include solar PV panels on the roof, EV charging, water conservation and energy\u00a0..."
                },
                {
                    "title": "Planning go ahead for green tenants at Gateway 14 - Mid Suffolk ...",
                    "link": "https://www.midsuffolk.gov.uk/w/planning-go-ahead-for-green-tenants-at-gateway-14",
                    "snippet": "Jul 18, 2024 ... With planning permission ... All high specification buildings on Gateway 14 include EV charging, LED lighting, solar PV, smart energy systems and\u00a0..."
                },
                {
                    "title": "Search and comment on a planning application - Mid Suffolk District ...",
                    "link": "https://www.midsuffolk.gov.uk/w/application-search-and-comment",
                    "snippet": "Material planning considerations are matters that are relevant when a planning decision is being made. They include, but are not limited to: Local, strategic\u00a0..."
                },
                {
                    "title": "Energy Efficiency and Historic Buildings \u2013 Fabric Upgrades and ...",
                    "link": "https://www.midsuffolk.gov.uk/documents/d/asset-library-54706/energy-efficiency-and-historic-buildings-fabric-upgrades-and-energy-generation",
                    "snippet": "They are also available in the form of solar slates. Requirement for Permission ... - Building Regulations on Fuel and Power \u2013 HM. Government, 2023. Conservation\u00a0..."
                },
                {
                    "title": "Conservation areas - Babergh District Council - babergh.gov.uk ...",
                    "link": "https://midsuffolk.gov.uk/en/web/babergh/conservation-areas",
                    "snippet": "... planning permission - which makes them 'permitted development'. However ... the installation of solar panels on a roof slope which fronts a highway; the\u00a0..."
                },
                {
                    "title": "National and Local Validation List: Part One",
                    "link": "https://www.midsuffolk.gov.uk/documents/d/asset-library-54706/lvl-review-part-1-householder-final-updated-31-10-23",
                    "snippet": "For Householder Planning Permission:- \u2022 A Design and Access Statement must ... o Solar panels. Page 12. 12 | Page. Babergh and Mid Suffolk District\u00a0..."
                },
                {
                    "title": "Planning Advice - Mid Suffolk District Council - babergh.gov.uk ...",
                    "link": "https://midsuffolk.gov.uk/w/free-online-planning-advice",
                    "snippet": "Advice about Residential and Commercial Development and Changes of Use. Residential Development: New houses always need planning permission, including if\u00a0..."
                }
            ],
            "count": 10,
            "executed_at": "2025-08-11T00:56:33+01:00"
        },
        "list_analysis": {
            "analysis_result": "{\n    \"raw_result\": {\n        \"Summary\": {\n            \"status\": \"RECOMMENDATIONS FOUND\",\n            \"totalItems\": \"10\",\n            \"recommendations\": \"5\"\n        },\n        \"Recommendations\": [\n            {\n                \"Number\": \"1\",\n                \"Title\": \"Do I need permission? - Mid Suffolk District Council - babergh.gov ...\",\n                \"Source\": \"https:\\/\\/www.midsuffolk.gov.uk\\/do-i-need-permission-\",\n                \"Key Strengths\": [\n                    \"Provides comprehensive information about planning permissions for residential changes.\",\n                    \"Easy to navigate and find relevant information.\"\n                ],\n                \"Confidence\": \"85\",\n                \"Reasoning\": \"This link directly addresses the question of whether permission is needed for making a change to one's home, which is what council customers might be seeking.\"\n            },\n            {\n                \"Number\": \"2\",\n                \"Title\": \"Planning - Babergh District Council - babergh.gov.uk \\/ midsuffolk ...\",\n                \"Source\": \"https:\\/\\/midsuffolk.gov.uk\\/en\\/web\\/babergh\\/planning\",\n                \"Key Strengths\": [\n                    \"Offers information on planning applications, pre-application advice, appeals, and enforcement.\",\n                    \"Has links to fees and charges for applying for planning permission.\"\n                ],\n                \"Confidence\": \"80\",\n                \"Reasoning\": \"This link covers a broad range of topics related to planning permits, providing council customers with detailed information in one place.\"\n            },\n            {\n                \"Number\": \"3\",\n                \"Title\": \"Search and comment on a planning application - Mid Suffolk District ...\",\n                \"Source\": \"https:\\/\\/www.midsuffolk.gov.uk\\/w\\/application-search-and-comment\",\n                \"Key Strengths\": [\n                    \"Allows users to search, view, and comment on planning applications.\",\n                    \"Provides resources for understanding material planning considerations.\"\n                ],\n                \"Confidence\": \"80\",\n                \"Reasoning\": \"By giving council customers the ability to search, view, and comment on planning applications, this link is useful not only for finding information but also contributing to the process.\"\n            },\n            {\n                \"Number\": \"4\",\n                \"Title\": \"National and Local Validation List: Part One\",\n                \"Source\": \"https:\\/\\/www.midsuffolk.gov.uk\\/documents\\/d\\/asset-library-54706\\/lvl-review-part-1-householder-final-updated-31-10-23\",\n                \"Key Strengths\": [\n                    \"Contains a comprehensive list of validation requirements for householder planning permission.\",\n                    \"Includes items relevant to solar panel installations.\"\n                ],\n                \"Confidence\": \"75\",\n                \"Reasoning\": \"This document provides an up-to-date and detailed validation list that includes specific details about solar panel installations, which could be of interest to council customers.\"\n            },\n            {\n                \"Number\": \"5\",\n                \"Title\": \"Planning Advice - Mid Suffolk District Council - babergh.gov.uk ...\",\n                \"Source\": \"https:\\/\\/midsuffolk.gov.uk\\/w\\/free-online-planning-advice\",\n                \"Key Strengths\": [\n                    \"Offers free online residential and commercial planning advice.\",\n                    \"Explains requirements for new houses, changes of use, and more.\"\n                ],\n                \"Confidence\": \"70\",\n                \"Reasoning\": \"The free planning advice provided by this link covers both residential and commercial developments as well as changes of use, making it a valuable resource for council customers.\"\n            }\n        ],\n        \"Analysis Notes\": \"Although only five recommendations were given, the remaining items were not discarded outright. A few contained relevant topics such as energy efficiency and conservation areas but did not directly address the need for council customer information on basic planning and permit issues.\",\n        \"Recommendations Notes\": \"These recommendations were chosen due to their direct relevance in addressing council customers' needs in obtaining planning information and navigating relevant processes.\"\n    },\n    \"has_recommendations\": \"RECOMMENDATIONS FOUND\",\n    \"confidence_scores\": [\n        \"85\",\n        \"80\",\n        \"80\",\n        \"75\",\n        \"70\"\n    ],\n    \"options\": {\n        \"max_recommendations\": 5,\n        \"min_confidence\": 60,\n        \"include_reasoning\": true,\n        \"output_format\": \"structured\"\n    },\n    \"average_confidence\": 78,\n    \"max_confidence\": \"85\"\n}",
            "pilot_result": " {\n  \"recommendations\": [\n    {\n      \"Number\": \"1\",\n      \"Title\": \"Do I need permission? - Mid Suffolk District Council - babergh.gov ...\",\n      \"Source\": \"https:\\/\\/www.midsuffolk.gov.uk\\/do-i-need-permission-\",\n      \"Reasoning\": \"This link directly addresses the question of whether permission is needed for making a change to one's home, which is what council customers might be seeking.\",\n      \"Confidence\": \"85\"\n    },\n    {\n      \"Number\": \"2\",\n      \"Title\": \"Planning - Babergh District Council - babergh.gov.uk \\/ midsuffolk ...\",\n      \"Source\": \"https:\\/\\/midsuffolk.gov.uk\\/en\\/web\\/babergh\\/planning\",\n      \"Reasoning\": \"This link covers a broad range of topics related to planning permits, providing council customers with detailed information in one place.\",\n      \"Confidence\": \"80\"\n    },\n    {\n      \"Number\": \"3\",\n      \"Title\": \"Search and comment on a planning application - Mid Suffolk District ...\",\n      \"Source\": \"https:\\/\\/www.midsuffolk.gov.uk\\/w\\/application-search-and-comment\",\n      \"Reasoning\": \"By giving council customers the ability to search, view, and comment on planning applications, this link is useful not only for finding information but also contributing to the process.\",\n      \"Confidence\": \"80\"\n    }\n  ]\n}",
            "decision": {
                "action": "continue",
                "confidence": 0.8,
                "selected_links": {
                    "id": "rec_1",
                    "url": "https://www.midsuffolk.gov.uk/do-i-need-permission-",
                    "title": "Do I need permission? - Mid Suffolk District Council - babergh.gov ...",
                    "confidence": 85,
                    "strengths": [
                        "Provides comprehensive information about planning permissions for residential changes.",
                        "Easy to navigate and find relevant information."
                    ],
                    "reasoning": "This link directly addresses the question of whether permission is needed for making a change to one's home, which is what council customers might be seeking.",
                    "rank": 1
                }
            },
            "executed_at": "2025-08-11T00:56:59+01:00"
        },
        "link_processing": [
            {
                "processed_links": [
                    {
                        "url": "https://www.midsuffolk.gov.uk/do-i-need-permission-",
                        "analysis": {
                            "url": "https://www.midsuffolk.gov.uk/do-i-need-permission-",
                            "context": {
                                "user_need": "access information",
                                "accessibility_priority": "medium",
                                "user_personas": [],
                                "fallback_required": true,
                                "context": {
                                    "search_topic": "planning permission solar panels",
                                    "persona": "council_customer",
                                    "need": "I'd like to install solar panels on my house and want to know if I need permission to have someone undertake this work.",
                                    "started_at": "2025-08-11T00:56:32+01:00",
                                    "search_parameters": {
                                        "query": "planning permission solar panels",
                                        "max_results": 5,
                                        "language": "en",
                                        "country": "uk"
                                    }
                                },
                                "persona": {
                                    "persona_type": "council_customer",
                                    "expertise_level": "intermediate",
                                    "patience_level": "medium",
                                    "search_intent": "find_council_services_information",
                                    "time_constraints": "moderate",
                                    "quality_expectations": "high",
                                    "accessibility_priority": "high",
                                    "content_preferences": [
                                        "official_sources",
                                        "accessible_formats",
                                        "current_information"
                                    ],
                                    "personas": [
                                        "general_public",
                                        "accessibility_aware"
                                    ]
                                }
                            },
                            "timestamp": "2025-08-11T00:56:59+01:00",
                            "fetch_attempted": true,
                            "fetch_successful": true,
                            "http_status": 200,
                            "content_type": "text/html;charset=UTF-8",
                            "content_length": 98417,
                            "response_time": 0.636,
                            "redirects": [],
                            "technical_assessment": {
                                "score": 90,
                                "max_score": 100,
                                "issues": [],
                                "strengths": [
                                    "Successful HTTP response (200)",
                                    "Fast response time (0.636s)",
                                    "Content successfully retrieved (98417 bytes)",
                                    "Direct access (no redirects)"
                                ],
                                "status_interpretation": {
                                    "status": "success",
                                    "action": "proceed",
                                    "confidence": 95
                                }
                            },
                            "accessibility_assessment": {
                                "score": 90,
                                "max_score": 100,
                                "issues": [],
                                "recommendations": [],
                                "content_type_assessment": {
                                    "accessibility_score": 90,
                                    "user_friendly": true,
                                    "requires_plugin": false,
                                    "mobile_compatible": true,
                                    "recommendation": "proceed"
                                },
                                "user_persona_impacts": []
                            },
                            "recommendation": {
                                "action": "proceed",
                                "confidence": 95,
                                "reason": "Link appears suitable for user needs",
                                "overall_score": 74,
                                "component_scores": {
                                    "technical": 90,
                                    "accessibility": 90,
                                    "match": 50
                                },
                                "next_steps": [
                                    "Follow the link to access the content"
                                ],
                                "alternatives_needed": false
                            }
                        },
                        "processing_time": 0.6377959251403809,
                        "status": "success"
                    }
                ],
                "failed_links": [],
                "executed_at": "2025-08-11T00:57:00+01:00"
            }
        ],
        "content_analysis": {
            "analyzed_content": [
                {
                    "url": "https://www.midsuffolk.gov.uk/do-i-need-permission-",
                    "analysis": null,
                    "content_type": "html",
                    "analysis_time": 5.255306005477905,
                    "status": "success"
                }
            ],
            "failed_analyses": [],
            "executed_at": "2025-08-11T00:57:11+01:00"
        },
        "journey_decision": {
            "journey_analysis": {
                "journey_id": "20250811_005632-midsuffolk.gov.uk",
                "analysis_timestamp": "2025-08-11T00:57:11+01:00",
                "analysis_duration": 0,
                "recommendation": "try_chat",
                "confidence": 75,
                "reasoning": "Poor Google search results quality - ChatScout may provide better content",
                "metrics": {
                    "basic": {
                        "total_steps": 6,
                        "duration_minutes": 0.65,
                        "tokens_consumed": 5582,
                        "tokens_remaining": 24418,
                        "token_utilization_percentage": 18.61,
                        "average_tokens_per_step": 930.33
                    },
                    "token_analysis": {
                        "status": "comfortable",
                        "remaining_percentage": 81.39,
                        "urgency_score": 0,
                        "estimated_remaining_steps": 26,
                        "consumption_rate": 930.33,
                        "should_conserve": false,
                        "emergency_stop_recommended": false
                    },
                    "progression_analysis": {
                        "total_steps": 6,
                        "step_types_distribution": {
                            "custom": 2,
                            "scout": 2,
                            "analyst": 2
                        },
                        "recent_steps_count": 5,
                        "recent_step_types": [
                            "scout",
                            "analyst",
                            "custom",
                            "scout",
                            "analyst"
                        ],
                        "successful_steps": 0,
                        "failed_steps": 0,
                        "success_rate": 0,
                        "repetitive_pattern_score": 2,
                        "shows_progress": false,
                        "stagnation_detected": false
                    },
                    "content_quality": {
                        "content_steps_count": 0,
                        "average_quality_score": 0,
                        "max_quality_score": 0,
                        "quality_scores": [],
                        "quality_trend": "error",
                        "unique_sources_count": 0,
                        "has_good_content": 0,
                        "consistent_good_content": 0,
                        "content_diversity": 1
                    },
                    "persona_analysis": {
                        "persona_type": "council_customer",
                        "expertise_level": "intermediate",
                        "patience_level": "medium",
                        "duration_fatigue_percentage": 9.29,
                        "steps_fatigue_percentage": 50,
                        "overall_fatigue_score": 50,
                        "expected_quality_threshold": 60,
                        "patience_exceeded": false,
                        "boredom_likely": false
                    },
                    "engagement_analysis": {
                        "duration_minutes": 0.65,
                        "total_steps": 6,
                        "boredom_indicators": {
                            "excessive_duration": false,
                            "too_many_steps": false,
                            "no_recent_progress": true,
                            "repetitive_failures": false
                        },
                        "boredom_score": 25,
                        "user_likely_bored": false,
                        "engagement_declining": false
                    },
                    "efficiency_analysis": {
                        "efficiency_score": 90,
                        "efficiency_factors": [
                            "Low token consumption per step",
                            "Fast completion time"
                        ],
                        "is_efficient": true,
                        "needs_optimization": false
                    }
                },
                "analysis_results": {
                    "stop_factors": [],
                    "continue_factors": [],
                    "risk_factors": [
                        "Poor content quality - consider changing strategy",
                        "Limited progress - may need strategy change"
                    ],
                    "optimization_suggestions": []
                },
                "alternative_actions": [
                    "continue_google",
                    "stopped_no_progress"
                ],
                "risk_factors": [
                    "AI content may lack specificity",
                    "Token consumption"
                ],
                "next_step_suggestions": [
                    "Use ChatScout for conceptual information",
                    "Combine AI content with found sources"
                ],
                "journey_summary": {
                    "journey_id": "20250811_005632-midsuffolk.gov.uk",
                    "start_time": "2025-08-11T00:56:32+01:00",
                    "current_time": "2025-08-11T00:57:11+01:00",
                    "duration_seconds": 39,
                    "status": "active",
                    "token_allocation": 30000,
                    "tokens_consumed": 5582,
                    "tokens_remaining": 24418,
                    "token_utilization_percentage": 18.61,
                    "token_status": "available",
                    "total_steps": 6,
                    "call_statistics": {
                        "scout": 2,
                        "analyst": 2,
                        "pilot": 0,
                        "custom": 2,
                        "total": 6
                    },
                    "token_statistics": {
                        "scout": {
                            "calls": 2,
                            "tokens": 2402,
                            "avg_per_call": 1201
                        },
                        "analyst": {
                            "calls": 2,
                            "tokens": 3180,
                            "avg_per_call": 1590
                        },
                        "pilot": {
                            "calls": 0,
                            "tokens": 0,
                            "avg_per_call": 0
                        },
                        "custom": {
                            "calls": 2,
                            "tokens": 0,
                            "avg_per_call": 0
                        }
                    },
                    "average_tokens_per_step": 930.33
                }
            },
            "final_decision": {
                "plan_id": "plan_689931d7ad4f1",
                "generated_at": "2025-08-11T00:57:11+01:00",
                "journey_id": "20250811_005632-midsuffolk.gov.uk",
                "based_on_analysis": {
                    "recommendation": "try_chat",
                    "confidence": 75,
                    "reasoning": "Poor Google search results quality - ChatScout may provide better content"
                },
                "primary_action": {
                    "action_type": "initiate_chat_scout",
                    "service": "chat_scout",
                    "description": "Switch to AI-generated content via ChatScout",
                    "execution_steps": [
                        "1. Analyze gaps in current content findings",
                        "2. Formulate comprehensive prompt for AI generation",
                        "3. Execute ChatScout with optimized parameters",
                        "4. Evaluate AI-generated content quality",
                        "5. Integrate with existing journey results"
                    ],
                    "parameters": {
                        "prompt": "Based on the search query: '' Provide comprehensive, accurate information that addresses the user's needs. Focus on practical, actionable insights and current information.",
                        "context": [],
                        "response_format": "structured",
                        "max_tokens": 2000
                    },
                    "estimated_token_cost": 2000,
                    "estimated_duration": 1.5,
                    "requirements_check": {
                        "all_requirements_met": true,
                        "individual_checks": {
                            "prompt": true,
                            "context": true
                        }
                    }
                },
                "fallback_plans": [],
                "resource_requirements": {
                    "estimated_tokens": 2000,
                    "estimated_duration": 1.5,
                    "memory_requirements": "low",
                    "external_service_calls": 1
                },
                "success_criteria": {
                    "primary_success_metric": "Action completed without errors",
                    "quality_thresholds": {
                        "minimum_quality_score": 60
                    },
                    "performance_criteria": {
                        "max_duration": 2.25
                    }
                },
                "risk_mitigation": {
                    "token_exhaustion": "Monitor token usage and stop if threshold exceeded",
                    "service_failure": "Implement retry logic with exponential backoff",
                    "poor_results": "Have fallback strategies ready"
                },
                "monitoring_points": {
                    "pre_execution": "Verify all requirements are met",
                    "mid_execution": "Check progress and resource consumption",
                    "post_execution": "Evaluate results and success metrics"
                },
                "options": {
                    "include_fallback_plans": true,
                    "include_resource_estimates": true,
                    "include_success_metrics": true
                }
            },
            "parsed_decision": {
                "recommendation": "try_chat",
                "confidence": 75,
                "reasoning": "Poor Google search results quality - ChatScout may provide better content"
            },
            "executed_at": "2025-08-11T00:57:11+01:00"
        }
    },
    "journey_outcome": true,
    "next_state": "try_chat",
    "reason": "Poor Google search results quality - ChatScout may provide better content",
    "execution_duration": 0.009,
    "journey_scout_summary": {
        "journey_id": "20250811_005632-midsuffolk.gov.uk",
        "start_time": "2025-08-11T00:56:32+01:00",
        "current_time": "2025-08-11T00:57:11+01:00",
        "duration_seconds": 39,
        "status": "active",
        "token_allocation": 30000,
        "tokens_consumed": 5582,
        "tokens_remaining": 24418,
        "token_utilization_percentage": 18.61,
        "token_status": "available",
        "total_steps": 7,
        "call_statistics": {
            "scout": 2,
            "analyst": 2,
            "pilot": 1,
            "custom": 2,
            "total": 7
        },
        "token_statistics": {
            "scout": {
                "calls": 2,
                "tokens": 2402,
                "avg_per_call": 1201
            },
            "analyst": {
                "calls": 2,
                "tokens": 3180,
                "avg_per_call": 1590
            },
            "pilot": {
                "calls": 1,
                "tokens": 0,
                "avg_per_call": 0
            },
            "custom": {
                "calls": 2,
                "tokens": 0,
                "avg_per_call": 0
            }
        },
        "average_tokens_per_step": 797.43
    }
}